clinicalomicsdb/.DS_Store
clinicalomicsdb/__init__.py
clinicalomicsdb/database_download.py
clinicalomicsdb/example.csv
clinicalomicsdb/exceptions.py
clinicalomicsdb/file_download.py
clinicalomicsdb/file_tools.py
clinicalomicsdb/main_clindb.py
clinicalomicsdb/main_clindb_k20.py
clinicalomicsdb/main_clindb_subtype_biomarkers.py
clinicalomicsdb/main_download_link.py
clinicalomicsdb/main_semi_clindb.py
clinicalomicsdb/main_single_biomarker.py
clinicalomicsdb/preset_semi_supervised_models.py
clinicalomicsdb/preset_supervised_models.py
clinicalomicsdb/preset_supervised_models_biomarkers.py
clinicalomicsdb/preset_supervised_models_k20.py
clinicalomicsdb/required_packages.txt
clinicalomicsdb/utils.py
clinicalomicsdb-0.4.8.dist-info/LICENSE
clinicalomicsdb-0.4.8.dist-info/WHEEL
clinicalomicsdb-0.4.8.dist-info/METADATA
clinicalomicsdb-0.4.8.dist-info/RECORD
